CATools-0.0.1.dist-info/DESCRIPTION.rst
CATools-0.0.1.dist-info/METADATA
CATools-0.0.1.dist-info/RECORD
CATools-0.0.1.dist-info/WHEEL
CATools-0.0.1.dist-info/metadata.json
CATools-0.0.1.dist-info/top_level.txt
catools/__init__.py
catools/rest.py
catools/soap/__init__.py
catools/soap/soap.py
