Metadata-Version: 2.0
Name: CATools
Version: 0.0.1
Summary: Helper Library for CA Service Desk Soap API
Home-page: https://github.com/jsarver/catools
Author: Josh Sarver
Author-email: josh.sarver@gmail.com
License: Copyright (c) 2016, Josh Sarver
Requires-Dist: pyyaml
Requires-Dist: suds-jurko
